mouse_anywhere/__init__.py
mouse_anywhere/mouse_anywhere2.dll
mouse_anywhere/wrapper.py
mouse_anywhere-0.2.6.dist-info/METADATA
mouse_anywhere-0.2.6.dist-info/WHEEL
mouse_anywhere-0.2.6.dist-info/top_level.txt
mouse_anywhere-0.2.6.dist-info/RECORD
