Metadata-Version: 2.1
Name: mouse-anywhere
Version: 0.2.6
Summary: A Python package for smooth mouse movement using a C library.
Home-page: https://github.com/wuhplaptop/mouse-anywhere
Author: wuhp
Author-email: wuhp@gmail.com
Project-URL: Bug Reports, https://github.com/wuhplaptop/mouse-anywhere/issues
Project-URL: Source, https://github.com/wuhplaptop/mouse-anywhere
Project-URL: Documentation, https://github.com/wuhplaptop/mouse-anywhere/wiki
Keywords: mouse automation cursor movement DLL
Classifier: Programming Language :: Python :: 3
Classifier: Operating System :: Microsoft :: Windows
Classifier: License :: OSI Approved :: MIT License
Classifier: Intended Audience :: Developers
Classifier: Topic :: Software Development :: Libraries
Classifier: Topic :: Software Development :: User Interfaces
Requires-Python: >=3.6
Provides-Extra: dev
Requires-Dist: pytest>=6.0.0; extra == "dev"
Requires-Dist: wheel; extra == "dev"
Requires-Dist: twine; extra == "dev"
